backend_dev_utils/__init__.py
backend_dev_utils/database_handlers/__init__.py
backend_dev_utils/database_handlers/multiple_database_handler.py
backend_dev_utils/database_handlers/single_database_handler.py
backend_dev_utils/design_patterns/__init__.py
backend_dev_utils/design_patterns/singletons/exceptions.py
backend_dev_utils/design_patterns/singletons/named_singleton/named_singleton_base.py
backend_dev_utils/design_patterns/singletons/named_singleton/named_singleton_meta.py
backend_dev_utils/design_patterns/singletons/singleton/singleton_base.py
backend_dev_utils/design_patterns/singletons/singleton/singleton_meta.py
backend_dev_utils/fastapi_helpers/__init__.py
backend_dev_utils/fastapi_helpers/fastapi_app.py
backend_dev_utils/fastapi_helpers/fastapi_route.py
backend_dev_utils/fastapi_helpers/fastapi_router.py
backend_dev_utils/http_helpers/exceptions.py
backend_dev_utils/http_helpers/url.py
backend_dev_utils/logger_manager/__init__.py
backend_dev_utils/logger_manager/logger_manager.py
backend_dev_utils-1.0.0.dist-info/METADATA
backend_dev_utils-1.0.0.dist-info/WHEEL
backend_dev_utils-1.0.0.dist-info/RECORD
