Metadata-Version: 2.1
Name: backend-dev-utils
Version: 1.0.0
Summary: Utility functions for python backend developers.
Home-page: https://backend-dev-utils.melikbugraozcelik.com
License: MIT
Author: melikbugra
Author-email: melik@melikbugraozcelik.com
Requires-Python: >=3.11,<4.0
Classifier: License :: OSI Approved :: MIT License
Classifier: Programming Language :: Python :: 3
Classifier: Programming Language :: Python :: 3.11
Classifier: Programming Language :: Python :: 3.12
Requires-Dist: fastapi[standard] (>=0.112.2,<0.113.0)
Requires-Dist: requests (>=2.32.3,<3.0.0)
Requires-Dist: sqlmodel (>=0.0.21,<0.0.22)
Project-URL: Author, https://melikbugraozcelik.com
Project-URL: Issues, https://github.com/melikbugra/backend-dev-utils/issues
